[
  {
    "Name": "Berlin Air",
    "AirportId": 1
  },
  {
    "Name": "Madrid Air Transport",
    "AirportId": 28
  },
  {
    "Name": "Mancherster Air Services",
    "AirportId": 27
  },
  {
    "Name": "Liverpool Air Services",
    "AirportId": 26
  },
  {
    "Name": "London Air Services",
    "AirportId": 25
  },
  {
    "Name": "Amsterdam Travel Services",
    "AirportId": 24
  },
  {
    "Name": "Milano Travel",
    "AirportId": 23
  },
  {
    "Name": "Palma De Malorka Air",
    "AirportId": 22
  },
  {
    "Name": "Samara Company",
    "AirportId": 21
  },
  {
    "Name": "Florencia to the best",
    "AirportId": 20
  },
  {
    "Name": "Silistra to the sky",
    "AirportId": 19
  },
  {
    "Name": "Burgas Airport Travel",
    "AirportId": 18
  },
  {
    "Name": "Varna Airport Services",
    "AirportId": 17
  },
  {
    "Name": "Sofia Made It To The Sky",
    "AirportId": 16
  },
  {
    "Name": "Dormund Airport Services",
    "AirportId": 15
  },
  {
    "Name": "Plovdiv Airport Services",
    "AirportId": 70
  },
  {
    "Name": "Sankt Peterburg Airport Services",
    "AirportId": 14
  },
  {
    "Name": "Frankfurt Sky",
    "AirportId": 12
  },
  {
    "Name": "Moskva Sky Services",
    "AirportId": 11
  },
  {
    "Name": "Munchen Airport Sky",
    "AirportId": 10
  },
  {
    "Name": "Marsilie Sky",
    "AirportId": 9
  },
  {
    "Name": "Hamburget Travel",
    "AirportId": 8
  },
  {
    "Name": "Bolnes Travel To The Sky",
    "AirportId": 7
  },
  {
    "Name": "Monreal Sky",
    "AirportId": 6
  },
  {
    "Name": "Vancuver Sky Services",
    "CitAirportIdyId": 5
  },
  {
    "Name": "Toronto Travel",
    "AirportId": 4
  },
  {
    "Name": "Atina Travel Agency ",
    "AirportId": 3
  },
  {
    "Name": "Ren Sky",
    "AirportId": 2
  },
  {
    "Name": "Novosibirsk Sky Transport",
    "AirportId": 29
  },
  {
    "Name": "Lil Flights",
    "AirportId": 30
  }
]
